dibs_datasource_csv/__init__.py
dibs_datasource_csv/datasource_csv.py
dibs_datasource_csv/utils/__init__.py
dibs_datasource_csv/utils/location_utils.py
dibs_datasource_csv/utils/utils_epwfile.py
dibs_datasource_csv/utils/utils_hkgeb.py
dibs_datasource_csv/utils/utils_normreader.py
dibs_datasource_csv/utils/utils_readcsv.py
dibs_datasource_csv/utils/utils_schedule.py
dibs_datasource_csv/utils/utils_tekreader.py
dibs_datasource_csv-1.0.1.dist-info/LICENSE
dibs_datasource_csv-1.0.1.dist-info/WHEEL
dibs_datasource_csv-1.0.1.dist-info/METADATA
dibs_datasource_csv-1.0.1.dist-info/RECORD
