Metadata-Version: 2.1
Name: dibs_datasource_csv
Version: 1.0.1
Summary: This package translates CSV date files to DIBS input. DIBS---Dynamic-ISO-Building-Simulator is a simulation program for calculating the space heating, occupancy hot water, cooling and electricity demand of German non-residential buildings. Further the DIBS calculates the heating value based energy uses, the primary energy and the greenhouse gas emission. The underlying resistance-capacity-model is based on the simplified hourly method of ISO 13790:2008.
Keywords: Building,Building-Stock,Non-Domestic,Non-Residential,Operational,Energy,Greenhouse Gas,Global Warming Potential,Simulation,Model,Germany,ISO 13790,5R1C
Author: Simon Knoll, Michael Hörner
Author-email: Julian Bischof <j.bischof@iwu.de>, Wail Samjouni <w.samjouni@iwu.de>, André Müller <a.mueller@iwu.de>, Jens Calisti <j.calisti@iwu.de>
Requires-Python: >=3.10.0
Classifier: Development Status :: 4 - Beta
Classifier: Programming Language :: Python
Requires-Dist: pandas == 2.2.1
Requires-Dist: numpy>1.22.4,<=2.0.0.dev0
Requires-Dist: dibs_computing_core
Requires-Dist: dibs_data == 1.0.1
Requires-Dist: openpyxl == 3.1.2
Requires-Dist: geopy == 2.4.0
Project-URL: Repository, https://github.com/IWUGERMANY/DibsDataSourceCSV
